discovery_connect/Connect.py
discovery_connect/__init__.py
discovery_connect-0.0.6.dist-info/METADATA
discovery_connect-0.0.6.dist-info/WHEEL
discovery_connect-0.0.6.dist-info/licenses/LICENSE
discovery_connect-0.0.6.dist-info/RECORD
