Metadata-Version: 2.3
Name: discovery-connect
Version: 0.0.6
Summary: Python interface for data exchange via the RetinAI Discovery API
Project-URL: Homepage, https://github.com/ikerian/discovery-connect
Project-URL: Issues, https://github.com/ikerian/discovery-connect/issues
Author-email: Antoine Letouzey <antoine.letouzey@retinai.com>
Classifier: License :: OSI Approved :: GNU General Public License v2 (GPLv2)
Classifier: Operating System :: OS Independent
Classifier: Programming Language :: Python :: 3
Requires-Python: >=3.8
Requires-Dist: requests>=2.31.0
